facebook_totem/__init__.py
facebook_totem/core.py
facebook_totem-1.dist-info/METADATA
facebook_totem-1.dist-info/WHEEL
facebook_totem-1.dist-info/top_level.txt
facebook_totem-1.dist-info/RECORD
